tfidfDE/__init__.py
tfidfDE/lemmata.csv
tfidfDE/stopwords.txt
tfidfDE/tfidfDE.py
tfidfDE-0.7.1.dist-info/DESCRIPTION.rst
tfidfDE-0.7.1.dist-info/METADATA
tfidfDE-0.7.1.dist-info/RECORD
tfidfDE-0.7.1.dist-info/WHEEL
tfidfDE-0.7.1.dist-info/metadata.json
tfidfDE-0.7.1.dist-info/top_level.txt
