Metadata-Version: 2.0
Name: tfidfDE
Version: 0.7.1
Summary: German tf-idf module.
Home-page: https://github.com/juliuste/tf-idf
Author: Julius Tens
Author-email: mail@julius-tens.de
License: MIT
Keywords: tf idf lemmatize tokenize
Platform: UNKNOWN
Classifier: Development Status :: 4 - Beta
Classifier: Intended Audience :: Developers
Classifier: License :: OSI Approved :: MIT License
Classifier: Programming Language :: Python :: 3
Classifier: Programming Language :: Python :: 3.3
Classifier: Programming Language :: Python :: 3.4
Classifier: Programming Language :: Python :: 3.5
